Metadata-Version: 1.0
Name: gaus-simdist
Version: 0.1
Summary: Gaussian distributions
Home-page: UNKNOWN
Author: ['udemy course']
Author-email: UNKNOWN
License: UNKNOWN
Platform: UNKNOWN
